{
    "p_1":{
        "nodes":[
            {
                "id":"18692064",
                "labels":[
                    "Company"
                ],
                "properties":{
                    "name":"上海建工集团股份有限公司",
                    "gid":"18692064"
                }
            },
            {
                "id":"3484794127",
                "labels":[
                    "Company"
                ],
                "properties":{
                    "name":"香港中央结算有限公司",
                    "gid":"3484794127"
                }
            },
            {
                "id":"616637723",
                "labels":[
                    "Company"
                ],
                "properties":{
                    "name":"贵州川恒化工股份有限公司",
                    "gid":"616637723"
                }
            },
            {
                "id":"2343197839",
                "labels":[
                    "Company"
                ],
                "properties":{
                    "name":"贵州福泉农村商业银行股份有限公司",
                    "gid":"2343197839"
                }
            },
            {
                "id":"1816042566&221425919",
                "labels":[
                    "Human"
                ],
                "properties":{
                    "name":"刘耘",
                    "gid":"1816042566"
                }
            },
            {
                "id":"221425919",
                "labels":[
                    "Company"
                ],
                "properties":{
                    "name":"贵州麒龙房地产开发集团有限公司",
                    "gid":"221425919"
                }
            },
            {
                "id":"3343041719",
                "labels":[
                    "Company"
                ],
                "properties":{
                    "name":"贵州麒龙恒力源置业有限公司",
                    "gid":"3343041719"
                }
            },
            {
                "id":"619391543",
                "labels":[
                    "Company"
                ],
                "properties":{
                    "name":"贵州恒力源实业有限公司",
                    "gid":"619391543"
                }
            },
            {
                "id":"1984908418&619391543",
                "labels":[
                    "Human"
                ],
                "properties":{
                    "name":"李振飞",
                    "gid":"1984908418"
                }
            },
            {
                "id":"3162969764",
                "labels":[
                    "Company"
                ],
                "properties":{
                    "name":"杭州雄途商贸有限公司",
                    "gid":"3162969764"
                }
            }
        ],
        "relationships":[
            {
                "type":"INVEST_C",
                "startNode":"3484794127",
                "endNode":"18692064",
                "properties":{
                    "labels":[
                        "参股"
                    ]
                }
            },
            {
                "type":"INVEST_C",
                "startNode":"3484794127",
                "endNode":"616637723",
                "properties":{
                    "labels":[
                        "参股"
                    ]
                }
            },
            {
                "type":"INVEST_C",
                "startNode":"616637723",
                "endNode":"2343197839",
                "properties":{
                    "labels":[
                        "参股"
                    ]
                }
            },
            {
                "type":"INVEST_H",
                "startNode":"1816042566&221425919",
                "endNode":"2343197839",
                "properties":{
                    "labels":[
                        "参股"
                    ]
                }
            },
            {
                "type":"OWN",
                "startNode":"1816042566&221425919",
                "endNode":"221425919",
                "properties":{
                    "labels":[
                        "法人"
                    ]
                }
            },
            {
                "type":"INVEST_C",
                "startNode":"221425919",
                "endNode":"3343041719",
                "properties":{
                    "labels":[
                        "参股"
                    ]
                }
            },
            {
                "type":"INVEST_C",
                "startNode":"619391543",
                "endNode":"3343041719",
                "properties":{
                    "labels":[
                        "参股"
                    ]
                }
            },
            {
                "type":"INVEST_H",
                "startNode":"1984908418&619391543",
                "endNode":"619391543",
                "properties":{
                    "labels":[
                        "参股"
                    ]
                }
            },
            {
                "type":"INVEST_H",
                "startNode":"1984908418&619391543",
                "endNode":"3162969764",
                "properties":{
                    "labels":[
                        "参股"
                    ]
                }
            },
            {
                "type":"SERVE",
                "startNode":"1984908418&619391543",
                "endNode":"3162969764",
                "properties":{
                    "labels":[
                        "监事"
                    ]
                }
            },
            {
                "type":"SERVE",
                "startNode":"1984908418&619391543",
                "endNode":"619391543",
                "properties":{
                    "labels":[
                        "董事"
                    ]
                }
            },
            {
                "type":"SERVE",
                "startNode":"1816042566&221425919",
                "endNode":"221425919",
                "properties":{
                    "labels":[
                        "执行董事"
                    ]
                }
            },
            {
                "type":"INVEST_H",
                "startNode":"1816042566&221425919",
                "endNode":"221425919",
                "properties":{
                    "labels":[
                        "参股"
                    ]
                }
            }
        ]
    },
    "p_2":{
        "nodes":[
            {
                "id":"18692064",
                "labels":[
                    "Company"
                ],
                "properties":{
                    "name":"上海建工集团股份有限公司",
                    "gid":"18692064"
                }
            },
            {
                "id":"236552539",
                "labels":[
                    "Company"
                ],
                "properties":{
                    "name":"上海中心大厦建设发展有限公司",
                    "gid":"236552539"
                }
            },
            {
                "id":"253508787",
                "labels":[
                    "Company"
                ],
                "properties":{
                    "name":"上海陆家嘴金融贸易区开发股份有限公司",
                    "gid":"253508787"
                }
            },
            {
                "id":"1763509876&253508787",
                "labels":[
                    "Human"
                ],
                "properties":{
                    "name":"乔文骏",
                    "gid":"1763509876"
                }
            },
            {
                "id":"3266585174",
                "labels":[
                    "Company"
                ],
                "properties":{
                    "name":"嘉兴跃马骏驰投资合伙企业（有限合伙）",
                    "gid":"3266585174"
                }
            },
            {
                "id":"2109498638&3343041719",
                "labels":[
                    "Human"
                ],
                "properties":{
                    "name":"纪超",
                    "gid":"2109498638"
                }
            },
            {
                "id":"3343041719",
                "labels":[
                    "Company"
                ],
                "properties":{
                    "name":"贵州麒龙恒力源置业有限公司",
                    "gid":"3343041719"
                }
            },
            {
                "id":"619391543",
                "labels":[
                    "Company"
                ],
                "properties":{
                    "name":"贵州恒力源实业有限公司",
                    "gid":"619391543"
                }
            },
            {
                "id":"1984908418&619391543",
                "labels":[
                    "Human"
                ],
                "properties":{
                    "name":"李振飞",
                    "gid":"1984908418"
                }
            },
            {
                "id":"3162969764",
                "labels":[
                    "Company"
                ],
                "properties":{
                    "name":"杭州雄途商贸有限公司",
                    "gid":"3162969764"
                }
            }
        ],
        "relationships":[
            {
                "type":"INVEST_C",
                "startNode":"18692064",
                "endNode":"236552539",
                "properties":{
                    "labels":[
                        "参股"
                    ]
                }
            },
            {
                "type":"INVEST_C",
                "startNode":"253508787",
                "endNode":"236552539",
                "properties":{
                    "labels":[
                        "参股"
                    ]
                }
            },
            {
                "type":"SERVE",
                "startNode":"1763509876&253508787",
                "endNode":"253508787",
                "properties":{
                    "labels":[
                        "董事"
                    ]
                }
            },
            {
                "type":"INVEST_H",
                "startNode":"1763509876&253508787",
                "endNode":"3266585174",
                "properties":{
                    "labels":[
                        "参股"
                    ]
                }
            },
            {
                "type":"INVEST_H",
                "startNode":"2109498638&3343041719",
                "endNode":"3266585174",
                "properties":{
                    "labels":[
                        "参股"
                    ]
                }
            },
            {
                "type":"SERVE",
                "startNode":"2109498638&3343041719",
                "endNode":"3343041719",
                "properties":{
                    "labels":[
                        "监事"
                    ]
                }
            },
            {
                "type":"INVEST_C",
                "startNode":"619391543",
                "endNode":"3343041719",
                "properties":{
                    "labels":[
                        "参股"
                    ]
                }
            },
            {
                "type":"INVEST_H",
                "startNode":"1984908418&619391543",
                "endNode":"619391543",
                "properties":{
                    "labels":[
                        "参股"
                    ]
                }
            },
            {
                "type":"INVEST_H",
                "startNode":"1984908418&619391543",
                "endNode":"3162969764",
                "properties":{
                    "labels":[
                        "参股"
                    ]
                }
            },
            {
                "type":"SERVE",
                "startNode":"1984908418&619391543",
                "endNode":"3162969764",
                "properties":{
                    "labels":[
                        "监事"
                    ]
                }
            },
            {
                "type":"SERVE",
                "startNode":"1984908418&619391543",
                "endNode":"619391543",
                "properties":{
                    "labels":[
                        "董事"
                    ]
                }
            }
        ]
    },
    "p_3":{
        "nodes":[
            {
                "id":"18692064",
                "labels":[
                    "Company"
                ],
                "properties":{
                    "name":"上海建工集团股份有限公司",
                    "gid":"18692064"
                }
            },
            {
                "id":"2310457667",
                "labels":[
                    "Company"
                ],
                "properties":{
                    "name":"中央汇金资产管理有限责任公司",
                    "gid":"2310457667"
                }
            },
            {
                "id":"253508787",
                "labels":[
                    "Company"
                ],
                "properties":{
                    "name":"上海陆家嘴金融贸易区开发股份有限公司",
                    "gid":"253508787"
                }
            },
            {
                "id":"1763509876&253508787",
                "labels":[
                    "Human"
                ],
                "properties":{
                    "name":"乔文骏",
                    "gid":"1763509876"
                }
            },
            {
                "id":"3266585174",
                "labels":[
                    "Company"
                ],
                "properties":{
                    "name":"嘉兴跃马骏驰投资合伙企业（有限合伙）",
                    "gid":"3266585174"
                }
            },
            {
                "id":"2109498638&3343041719",
                "labels":[
                    "Human"
                ],
                "properties":{
                    "name":"纪超",
                    "gid":"2109498638"
                }
            },
            {
                "id":"3343041719",
                "labels":[
                    "Company"
                ],
                "properties":{
                    "name":"贵州麒龙恒力源置业有限公司",
                    "gid":"3343041719"
                }
            },
            {
                "id":"619391543",
                "labels":[
                    "Company"
                ],
                "properties":{
                    "name":"贵州恒力源实业有限公司",
                    "gid":"619391543"
                }
            },
            {
                "id":"1984908418&619391543",
                "labels":[
                    "Human"
                ],
                "properties":{
                    "name":"李振飞",
                    "gid":"1984908418"
                }
            },
            {
                "id":"3162969764",
                "labels":[
                    "Company"
                ],
                "properties":{
                    "name":"杭州雄途商贸有限公司",
                    "gid":"3162969764"
                }
            }
        ],
        "relationships":[
            {
                "type":"INVEST_C",
                "startNode":"2310457667",
                "endNode":"18692064",
                "properties":{
                    "labels":[
                        "参股"
                    ]
                }
            },
            {
                "type":"INVEST_C",
                "startNode":"2310457667",
                "endNode":"253508787",
                "properties":{
                    "labels":[
                        "参股"
                    ]
                }
            },
            {
                "type":"SERVE",
                "startNode":"1763509876&253508787",
                "endNode":"253508787",
                "properties":{
                    "labels":[
                        "董事"
                    ]
                }
            },
            {
                "type":"INVEST_H",
                "startNode":"1763509876&253508787",
                "endNode":"3266585174",
                "properties":{
                    "labels":[
                        "参股"
                    ]
                }
            },
            {
                "type":"INVEST_H",
                "startNode":"2109498638&3343041719",
                "endNode":"3266585174",
                "properties":{
                    "labels":[
                        "参股"
                    ]
                }
            },
            {
                "type":"SERVE",
                "startNode":"2109498638&3343041719",
                "endNode":"3343041719",
                "properties":{
                    "labels":[
                        "监事"
                    ]
                }
            },
            {
                "type":"INVEST_C",
                "startNode":"619391543",
                "endNode":"3343041719",
                "properties":{
                    "labels":[
                        "参股"
                    ]
                }
            },
            {
                "type":"INVEST_H",
                "startNode":"1984908418&619391543",
                "endNode":"619391543",
                "properties":{
                    "labels":[
                        "参股"
                    ]
                }
            },
            {
                "type":"INVEST_H",
                "startNode":"1984908418&619391543",
                "endNode":"3162969764",
                "properties":{
                    "labels":[
                        "参股"
                    ]
                }
            },
            {
                "type":"SERVE",
                "startNode":"1984908418&619391543",
                "endNode":"3162969764",
                "properties":{
                    "labels":[
                        "监事"
                    ]
                }
            },
            {
                "type":"SERVE",
                "startNode":"1984908418&619391543",
                "endNode":"619391543",
                "properties":{
                    "labels":[
                        "董事"
                    ]
                }
            }
        ]
    },
    "p_4":{
        "nodes":[
            {
                "id":"18692064",
                "labels":[
                    "Company"
                ],
                "properties":{
                    "name":"上海建工集团股份有限公司",
                    "gid":"18692064"
                }
            },
            {
                "id":"18499007",
                "labels":[
                    "Company"
                ],
                "properties":{
                    "name":"中国证券金融股份有限公司",
                    "gid":"18499007"
                }
            },
            {
                "id":"253508787",
                "labels":[
                    "Company"
                ],
                "properties":{
                    "name":"上海陆家嘴金融贸易区开发股份有限公司",
                    "gid":"253508787"
                }
            },
            {
                "id":"1763509876&253508787",
                "labels":[
                    "Human"
                ],
                "properties":{
                    "name":"乔文骏",
                    "gid":"1763509876"
                }
            },
            {
                "id":"3266585174",
                "labels":[
                    "Company"
                ],
                "properties":{
                    "name":"嘉兴跃马骏驰投资合伙企业（有限合伙）",
                    "gid":"3266585174"
                }
            },
            {
                "id":"2109498638&3343041719",
                "labels":[
                    "Human"
                ],
                "properties":{
                    "name":"纪超",
                    "gid":"2109498638"
                }
            },
            {
                "id":"3343041719",
                "labels":[
                    "Company"
                ],
                "properties":{
                    "name":"贵州麒龙恒力源置业有限公司",
                    "gid":"3343041719"
                }
            },
            {
                "id":"619391543",
                "labels":[
                    "Company"
                ],
                "properties":{
                    "name":"贵州恒力源实业有限公司",
                    "gid":"619391543"
                }
            },
            {
                "id":"1984908418&619391543",
                "labels":[
                    "Human"
                ],
                "properties":{
                    "name":"李振飞",
                    "gid":"1984908418"
                }
            },
            {
                "id":"3162969764",
                "labels":[
                    "Company"
                ],
                "properties":{
                    "name":"杭州雄途商贸有限公司",
                    "gid":"3162969764"
                }
            }
        ],
        "relationships":[
            {
                "type":"INVEST_C",
                "startNode":"18499007",
                "endNode":"18692064",
                "properties":{
                    "labels":[
                        "参股"
                    ]
                }
            },
            {
                "type":"INVEST_C",
                "startNode":"18499007",
                "endNode":"253508787",
                "properties":{
                    "labels":[
                        "参股"
                    ]
                }
            },
            {
                "type":"SERVE",
                "startNode":"1763509876&253508787",
                "endNode":"253508787",
                "properties":{
                    "labels":[
                        "董事"
                    ]
                }
            },
            {
                "type":"INVEST_H",
                "startNode":"1763509876&253508787",
                "endNode":"3266585174",
                "properties":{
                    "labels":[
                        "参股"
                    ]
                }
            },
            {
                "type":"INVEST_H",
                "startNode":"2109498638&3343041719",
                "endNode":"3266585174",
                "properties":{
                    "labels":[
                        "参股"
                    ]
                }
            },
            {
                "type":"SERVE",
                "startNode":"2109498638&3343041719",
                "endNode":"3343041719",
                "properties":{
                    "labels":[
                        "监事"
                    ]
                }
            },
            {
                "type":"INVEST_C",
                "startNode":"619391543",
                "endNode":"3343041719",
                "properties":{
                    "labels":[
                        "参股"
                    ]
                }
            },
            {
                "type":"INVEST_H",
                "startNode":"1984908418&619391543",
                "endNode":"619391543",
                "properties":{
                    "labels":[
                        "参股"
                    ]
                }
            },
            {
                "type":"INVEST_H",
                "startNode":"1984908418&619391543",
                "endNode":"3162969764",
                "properties":{
                    "labels":[
                        "参股"
                    ]
                }
            },
            {
                "type":"SERVE",
                "startNode":"1984908418&619391543",
                "endNode":"3162969764",
                "properties":{
                    "labels":[
                        "监事"
                    ]
                }
            },
            {
                "type":"SERVE",
                "startNode":"1984908418&619391543",
                "endNode":"619391543",
                "properties":{
                    "labels":[
                        "董事"
                    ]
                }
            }
        ]
    },
    "p_5":{
        "nodes":[
            {
                "id":"18692064",
                "labels":[
                    "Company"
                ],
                "properties":{
                    "name":"上海建工集团股份有限公司",
                    "gid":"18692064"
                }
            },
            {
                "id":"433370866",
                "labels":[
                    "Company"
                ],
                "properties":{
                    "name":"上海国盛（集团）有限公司",
                    "gid":"433370866"
                }
            },
            {
                "id":"3472584239",
                "labels":[
                    "Company"
                ],
                "properties":{
                    "name":"上海文化产业发展投资基金管理有限公司",
                    "gid":"3472584239"
                }
            },
            {
                "id":"2145035202&3266585174",
                "labels":[
                    "Human"
                ],
                "properties":{
                    "name":"葛永彬",
                    "gid":"2145035202"
                }
            },
            {
                "id":"3266585174",
                "labels":[
                    "Company"
                ],
                "properties":{
                    "name":"嘉兴跃马骏驰投资合伙企业（有限合伙）",
                    "gid":"3266585174"
                }
            },
            {
                "id":"2109498638&3343041719",
                "labels":[
                    "Human"
                ],
                "properties":{
                    "name":"纪超",
                    "gid":"2109498638"
                }
            },
            {
                "id":"3343041719",
                "labels":[
                    "Company"
                ],
                "properties":{
                    "name":"贵州麒龙恒力源置业有限公司",
                    "gid":"3343041719"
                }
            },
            {
                "id":"619391543",
                "labels":[
                    "Company"
                ],
                "properties":{
                    "name":"贵州恒力源实业有限公司",
                    "gid":"619391543"
                }
            },
            {
                "id":"1984908418&619391543",
                "labels":[
                    "Human"
                ],
                "properties":{
                    "name":"李振飞",
                    "gid":"1984908418"
                }
            },
            {
                "id":"3162969764",
                "labels":[
                    "Company"
                ],
                "properties":{
                    "name":"杭州雄途商贸有限公司",
                    "gid":"3162969764"
                }
            }
        ],
        "relationships":[
            {
                "type":"INVEST_C",
                "startNode":"433370866",
                "endNode":"18692064",
                "properties":{
                    "labels":[
                        "参股"
                    ]
                }
            },
            {
                "type":"INVEST_C",
                "startNode":"433370866",
                "endNode":"3472584239",
                "properties":{
                    "labels":[
                        "参股"
                    ]
                }
            },
            {
                "type":"SERVE",
                "startNode":"2145035202&3266585174",
                "endNode":"3472584239",
                "properties":{
                    "labels":[
                        "董事"
                    ]
                }
            },
            {
                "type":"INVEST_H",
                "startNode":"2145035202&3266585174",
                "endNode":"3266585174",
                "properties":{
                    "labels":[
                        "参股"
                    ]
                }
            },
            {
                "type":"INVEST_H",
                "startNode":"2109498638&3343041719",
                "endNode":"3266585174",
                "properties":{
                    "labels":[
                        "参股"
                    ]
                }
            },
            {
                "type":"SERVE",
                "startNode":"2109498638&3343041719",
                "endNode":"3343041719",
                "properties":{
                    "labels":[
                        "监事"
                    ]
                }
            },
            {
                "type":"INVEST_C",
                "startNode":"619391543",
                "endNode":"3343041719",
                "properties":{
                    "labels":[
                        "参股"
                    ]
                }
            },
            {
                "type":"INVEST_H",
                "startNode":"1984908418&619391543",
                "endNode":"619391543",
                "properties":{
                    "labels":[
                        "参股"
                    ]
                }
            },
            {
                "type":"INVEST_H",
                "startNode":"1984908418&619391543",
                "endNode":"3162969764",
                "properties":{
                    "labels":[
                        "参股"
                    ]
                }
            },
            {
                "type":"SERVE",
                "startNode":"1984908418&619391543",
                "endNode":"3162969764",
                "properties":{
                    "labels":[
                        "监事"
                    ]
                }
            },
            {
                "type":"SERVE",
                "startNode":"1984908418&619391543",
                "endNode":"619391543",
                "properties":{
                    "labels":[
                        "董事"
                    ]
                }
            }
        ]
    },
    "p_0":{
        "nodes":[
            {
                "id":"1763509876&253508787",
                "labels":[
                    "Human"
                ],
                "properties":{
                    "name":"乔文骏",
                    "gid":"1763509876"
                }
            },
            {
                "id":"2145035202&3266585174",
                "labels":[
                    "Human"
                ],
                "properties":{
                    "name":"葛永彬",
                    "gid":"2145035202"
                }
            },
            {
                "id":"236552539",
                "labels":[
                    "Company"
                ],
                "properties":{
                    "name":"上海中心大厦建设发展有限公司",
                    "gid":"236552539"
                }
            },
            {
                "id":"2310457667",
                "labels":[
                    "Company"
                ],
                "properties":{
                    "name":"中央汇金资产管理有限责任公司",
                    "gid":"2310457667"
                }
            },
            {
                "id":"253508787",
                "labels":[
                    "Company"
                ],
                "properties":{
                    "name":"上海陆家嘴金融贸易区开发股份有限公司",
                    "gid":"253508787"
                }
            },
            {
                "id":"1984908418&619391543",
                "labels":[
                    "Human"
                ],
                "properties":{
                    "name":"李振飞",
                    "gid":"1984908418"
                }
            },
            {
                "id":"619391543",
                "labels":[
                    "Company"
                ],
                "properties":{
                    "name":"贵州恒力源实业有限公司",
                    "gid":"619391543"
                }
            },
            {
                "id":"3343041719",
                "labels":[
                    "Company"
                ],
                "properties":{
                    "name":"贵州麒龙恒力源置业有限公司",
                    "gid":"3343041719"
                }
            },
            {
                "id":"2109498638&3343041719",
                "labels":[
                    "Human"
                ],
                "properties":{
                    "name":"纪超",
                    "gid":"2109498638"
                }
            },
            {
                "id":"433370866",
                "labels":[
                    "Company"
                ],
                "properties":{
                    "name":"上海国盛（集团）有限公司",
                    "gid":"433370866"
                }
            },
            {
                "id":"616637723",
                "labels":[
                    "Company"
                ],
                "properties":{
                    "name":"贵州川恒化工股份有限公司",
                    "gid":"616637723"
                }
            },
            {
                "id":"221425919",
                "labels":[
                    "Company"
                ],
                "properties":{
                    "name":"贵州麒龙房地产开发集团有限公司",
                    "gid":"221425919"
                }
            },
            {
                "id":"3266585174",
                "labels":[
                    "Company"
                ],
                "properties":{
                    "name":"嘉兴跃马骏驰投资合伙企业（有限合伙）",
                    "gid":"3266585174"
                }
            },
            {
                "id":"18499007",
                "labels":[
                    "Company"
                ],
                "properties":{
                    "name":"中国证券金融股份有限公司",
                    "gid":"18499007"
                }
            },
            {
                "id":"1816042566&221425919",
                "labels":[
                    "Human"
                ],
                "properties":{
                    "name":"刘耘",
                    "gid":"1816042566"
                }
            },
            {
                "id":"3472584239",
                "labels":[
                    "Company"
                ],
                "properties":{
                    "name":"上海文化产业发展投资基金管理有限公司",
                    "gid":"3472584239"
                }
            },
            {
                "id":"2343197839",
                "labels":[
                    "Company"
                ],
                "properties":{
                    "name":"贵州福泉农村商业银行股份有限公司",
                    "gid":"2343197839"
                }
            },
            {
                "id":"3162969764",
                "labels":[
                    "Company"
                ],
                "properties":{
                    "name":"杭州雄途商贸有限公司",
                    "gid":"3162969764"
                }
            },
            {
                "id":"3484794127",
                "labels":[
                    "Company"
                ],
                "properties":{
                    "name":"香港中央结算有限公司",
                    "gid":"3484794127"
                }
            },
            {
                "id":"18692064",
                "labels":[
                    "Company"
                ],
                "properties":{
                    "name":"上海建工集团股份有限公司",
                    "gid":"18692064"
                }
            }
        ],
        "relationships":[
            {
                "type":"INVEST_C",
                "startNode":"18692064",
                "endNode":"236552539",
                "properties":{
                    "labels":[
                        "参股"
                    ]
                }
            },
            {
                "type":"INVEST_C",
                "startNode":"221425919",
                "endNode":"3343041719",
                "properties":{
                    "labels":[
                        "参股"
                    ]
                }
            },
            {
                "type":"INVEST_C",
                "startNode":"433370866",
                "endNode":"18692064",
                "properties":{
                    "labels":[
                        "参股"
                    ]
                }
            },
            {
                "type":"SERVE",
                "startNode":"1984908418&619391543",
                "endNode":"3162969764",
                "properties":{
                    "labels":[
                        "监事"
                    ]
                }
            },
            {
                "type":"INVEST_C",
                "startNode":"18499007",
                "endNode":"253508787",
                "properties":{
                    "labels":[
                        "参股"
                    ]
                }
            },
            {
                "type":"INVEST_H",
                "startNode":"1984908418&619391543",
                "endNode":"3162969764",
                "properties":{
                    "labels":[
                        "参股"
                    ]
                }
            },
            {
                "type":"INVEST_C",
                "startNode":"616637723",
                "endNode":"2343197839",
                "properties":{
                    "labels":[
                        "参股"
                    ]
                }
            },
            {
                "type":"INVEST_H",
                "startNode":"1763509876&253508787",
                "endNode":"3266585174",
                "properties":{
                    "labels":[
                        "参股"
                    ]
                }
            },
            {
                "type":"INVEST_C",
                "startNode":"2310457667",
                "endNode":"253508787",
                "properties":{
                    "labels":[
                        "参股"
                    ]
                }
            },
            {
                "type":"INVEST_C",
                "startNode":"3484794127",
                "endNode":"18692064",
                "properties":{
                    "labels":[
                        "参股"
                    ]
                }
            },
            {
                "type":"SERVE",
                "startNode":"2145035202&3266585174",
                "endNode":"3472584239",
                "properties":{
                    "labels":[
                        "董事"
                    ]
                }
            },
            {
                "type":"SERVE",
                "startNode":"1763509876&253508787",
                "endNode":"253508787",
                "properties":{
                    "labels":[
                        "董事"
                    ]
                }
            },
            {
                "type":"INVEST_C",
                "startNode":"2310457667",
                "endNode":"18692064",
                "properties":{
                    "labels":[
                        "参股"
                    ]
                }
            },
            {
                "type":"OWN",
                "startNode":"1816042566&221425919",
                "endNode":"221425919",
                "properties":{
                    "labels":[
                        "法人"
                    ]
                }
            },
            {
                "type":"INVEST_H",
                "startNode":"2145035202&3266585174",
                "endNode":"3266585174",
                "properties":{
                    "labels":[
                        "参股"
                    ]
                }
            },
            {
                "type":"INVEST_H",
                "startNode":"2109498638&3343041719",
                "endNode":"3266585174",
                "properties":{
                    "labels":[
                        "参股"
                    ]
                }
            },
            {
                "type":"INVEST_C",
                "startNode":"18499007",
                "endNode":"18692064",
                "properties":{
                    "labels":[
                        "参股"
                    ]
                }
            },
            {
                "type":"INVEST_H",
                "startNode":"1984908418&619391543",
                "endNode":"619391543",
                "properties":{
                    "labels":[
                        "参股"
                    ]
                }
            },
            {
                "type":"INVEST_C",
                "startNode":"3484794127",
                "endNode":"616637723",
                "properties":{
                    "labels":[
                        "参股"
                    ]
                }
            },
            {
                "type":"INVEST_C",
                "startNode":"619391543",
                "endNode":"3343041719",
                "properties":{
                    "labels":[
                        "参股"
                    ]
                }
            },
            {
                "type":"SERVE",
                "startNode":"2109498638&3343041719",
                "endNode":"3343041719",
                "properties":{
                    "labels":[
                        "监事"
                    ]
                }
            },
            {
                "type":"INVEST_H",
                "startNode":"1816042566&221425919",
                "endNode":"2343197839",
                "properties":{
                    "labels":[
                        "参股"
                    ]
                }
            },
            {
                "type":"SERVE",
                "startNode":"1984908418&619391543",
                "endNode":"619391543",
                "properties":{
                    "labels":[
                        "董事"
                    ]
                }
            },
            {
                "type":"INVEST_C",
                "startNode":"253508787",
                "endNode":"236552539",
                "properties":{
                    "labels":[
                        "参股"
                    ]
                }
            },
            {
                "type":"SERVE",
                "startNode":"1816042566&221425919",
                "endNode":"221425919",
                "properties":{
                    "labels":[
                        "执行董事"
                    ]
                }
            },
            {
                "type":"INVEST_C",
                "startNode":"433370866",
                "endNode":"3472584239",
                "properties":{
                    "labels":[
                        "参股"
                    ]
                }
            },
            {
                "type":"INVEST_H",
                "startNode":"1816042566&221425919",
                "endNode":"221425919",
                "properties":{
                    "labels":[
                        "参股"
                    ]
                }
            }
        ]
    }
}