{
    "p_1":{
        "nodes":[
            {
                "id":"3128510407",
                "labels":[
                    "Company"
                ],
                "properties":{
                    "name":"中国建筑集团有限公司",
                    "gid":"3128510407"
                }
            },
            {
                "id":"1883105271&717278775",
                "labels":[
                    "Human"
                ],
                "properties":{
                    "name":"孙震",
                    "gid":"1883105271"
                }
            },
            {
                "id":"717278775",
                "labels":[
                    "Company"
                ],
                "properties":{
                    "name":"中建资本控股有限公司",
                    "gid":"717278775"
                }
            },
            {
                "id":"373897708",
                "labels":[
                    "Company"
                ],
                "properties":{
                    "name":"安徽国元投资有限责任公司",
                    "gid":"373897708"
                }
            },
            {
                "id":"2349394141",
                "labels":[
                    "Company"
                ],
                "properties":{
                    "name":"安徽新力金融股份有限公司",
                    "gid":"2349394141"
                }
            },
            {
                "id":"499395113",
                "labels":[
                    "Company"
                ],
                "properties":{
                    "name":"合肥德善小额贷款股份有限公司",
                    "gid":"499395113"
                }
            },
            {
                "id":"518729470",
                "labels":[
                    "Company"
                ],
                "properties":{
                    "name":"肥东县供销社泰昌资产管理有限公司",
                    "gid":"518729470"
                }
            },
            {
                "id":"4118865664",
                "labels":[
                    "Company"
                ],
                "properties":{
                    "name":"安徽润博仓储有限公司",
                    "gid":"4118865664"
                }
            },
            {
                "id":"1826156840&4118865664",
                "labels":[
                    "Human"
                ],
                "properties":{
                    "name":"卢向阳",
                    "gid":"1826156840"
                }
            },
            {
                "id":"3228082921",
                "labels":[
                    "Company"
                ],
                "properties":{
                    "name":"安徽大沙贸易有限公司",
                    "gid":"3228082921"
                }
            }
        ],
        "relationships":[
            {
                "type":"SERVE",
                "startNode":"1883105271&717278775",
                "endNode":"3128510407",
                "properties":{
                    "labels":[
                        "监事"
                    ]
                }
            },
            {
                "type":"SERVE",
                "startNode":"1883105271&717278775",
                "endNode":"717278775",
                "properties":{
                    "labels":[
                        "执行董事,总经理"
                    ]
                }
            },
            {
                "type":"INVEST_C",
                "startNode":"717278775",
                "endNode":"373897708",
                "properties":{
                    "labels":[
                        "参股"
                    ]
                }
            },
            {
                "type":"INVEST_C",
                "startNode":"2349394141",
                "endNode":"373897708",
                "properties":{
                    "labels":[
                        "参股"
                    ]
                }
            },
            {
                "type":"INVEST_C",
                "startNode":"2349394141",
                "endNode":"499395113",
                "properties":{
                    "labels":[
                        "参股"
                    ]
                }
            },
            {
                "type":"INVEST_C",
                "startNode":"518729470",
                "endNode":"499395113",
                "properties":{
                    "labels":[
                        "参股"
                    ]
                }
            },
            {
                "type":"INVEST_C",
                "startNode":"518729470",
                "endNode":"4118865664",
                "properties":{
                    "labels":[
                        "参股"
                    ]
                }
            },
            {
                "type":"INVEST_H",
                "startNode":"1826156840&4118865664",
                "endNode":"4118865664",
                "properties":{
                    "labels":[
                        "参股"
                    ]
                }
            },
            {
                "type":"INVEST_H",
                "startNode":"1826156840&4118865664",
                "endNode":"3228082921",
                "properties":{
                    "labels":[
                        "参股"
                    ]
                }
            },
            {
                "type":"SERVE",
                "startNode":"1826156840&4118865664",
                "endNode":"4118865664",
                "properties":{
                    "labels":[
                        "执行董事兼总经理"
                    ]
                }
            },
            {
                "type":"OWN",
                "startNode":"1826156840&4118865664",
                "endNode":"4118865664",
                "properties":{
                    "labels":[
                        "法人"
                    ]
                }
            },
            {
                "type":"OWN",
                "startNode":"1883105271&717278775",
                "endNode":"717278775",
                "properties":{
                    "labels":[
                        "法人"
                    ]
                }
            }
        ]
    },
    "p_2":{
        "nodes":[
            {
                "id":"3128510407",
                "labels":[
                    "Company"
                ],
                "properties":{
                    "name":"中国建筑集团有限公司",
                    "gid":"3128510407"
                }
            },
            {
                "id":"12321232",
                "labels":[
                    "Company"
                ],
                "properties":{
                    "name":"中国建筑股份有限公司",
                    "gid":"12321232"
                }
            },
            {
                "id":"717278775",
                "labels":[
                    "Company"
                ],
                "properties":{
                    "name":"中建资本控股有限公司",
                    "gid":"717278775"
                }
            },
            {
                "id":"373897708",
                "labels":[
                    "Company"
                ],
                "properties":{
                    "name":"安徽国元投资有限责任公司",
                    "gid":"373897708"
                }
            },
            {
                "id":"2349394141",
                "labels":[
                    "Company"
                ],
                "properties":{
                    "name":"安徽新力金融股份有限公司",
                    "gid":"2349394141"
                }
            },
            {
                "id":"499395113",
                "labels":[
                    "Company"
                ],
                "properties":{
                    "name":"合肥德善小额贷款股份有限公司",
                    "gid":"499395113"
                }
            },
            {
                "id":"518729470",
                "labels":[
                    "Company"
                ],
                "properties":{
                    "name":"肥东县供销社泰昌资产管理有限公司",
                    "gid":"518729470"
                }
            },
            {
                "id":"4118865664",
                "labels":[
                    "Company"
                ],
                "properties":{
                    "name":"安徽润博仓储有限公司",
                    "gid":"4118865664"
                }
            },
            {
                "id":"1826156840&4118865664",
                "labels":[
                    "Human"
                ],
                "properties":{
                    "name":"卢向阳",
                    "gid":"1826156840"
                }
            },
            {
                "id":"3228082921",
                "labels":[
                    "Company"
                ],
                "properties":{
                    "name":"安徽大沙贸易有限公司",
                    "gid":"3228082921"
                }
            }
        ],
        "relationships":[
            {
                "type":"INVEST_C",
                "startNode":"3128510407",
                "endNode":"12321232",
                "properties":{
                    "labels":[
                        "参股"
                    ]
                }
            },
            {
                "type":"INVEST_C",
                "startNode":"12321232",
                "endNode":"717278775",
                "properties":{
                    "labels":[
                        "参股"
                    ]
                }
            },
            {
                "type":"INVEST_C",
                "startNode":"717278775",
                "endNode":"373897708",
                "properties":{
                    "labels":[
                        "参股"
                    ]
                }
            },
            {
                "type":"INVEST_C",
                "startNode":"2349394141",
                "endNode":"373897708",
                "properties":{
                    "labels":[
                        "参股"
                    ]
                }
            },
            {
                "type":"INVEST_C",
                "startNode":"2349394141",
                "endNode":"499395113",
                "properties":{
                    "labels":[
                        "参股"
                    ]
                }
            },
            {
                "type":"INVEST_C",
                "startNode":"518729470",
                "endNode":"499395113",
                "properties":{
                    "labels":[
                        "参股"
                    ]
                }
            },
            {
                "type":"INVEST_C",
                "startNode":"518729470",
                "endNode":"4118865664",
                "properties":{
                    "labels":[
                        "参股"
                    ]
                }
            },
            {
                "type":"INVEST_H",
                "startNode":"1826156840&4118865664",
                "endNode":"4118865664",
                "properties":{
                    "labels":[
                        "参股"
                    ]
                }
            },
            {
                "type":"INVEST_H",
                "startNode":"1826156840&4118865664",
                "endNode":"3228082921",
                "properties":{
                    "labels":[
                        "参股"
                    ]
                }
            },
            {
                "type":"SERVE",
                "startNode":"1826156840&4118865664",
                "endNode":"4118865664",
                "properties":{
                    "labels":[
                        "执行董事兼总经理"
                    ]
                }
            },
            {
                "type":"OWN",
                "startNode":"1826156840&4118865664",
                "endNode":"4118865664",
                "properties":{
                    "labels":[
                        "法人"
                    ]
                }
            }
        ]
    },
    "p_3":{
        "nodes":[
            {
                "id":"3128510407",
                "labels":[
                    "Company"
                ],
                "properties":{
                    "name":"中国建筑集团有限公司",
                    "gid":"3128510407"
                }
            },
            {
                "id":"12321232",
                "labels":[
                    "Company"
                ],
                "properties":{
                    "name":"中国建筑股份有限公司",
                    "gid":"12321232"
                }
            },
            {
                "id":"3484794127",
                "labels":[
                    "Company"
                ],
                "properties":{
                    "name":"香港中央结算有限公司",
                    "gid":"3484794127"
                }
            },
            {
                "id":"16845043",
                "labels":[
                    "Company"
                ],
                "properties":{
                    "name":"中信建投证券股份有限公司",
                    "gid":"16845043"
                }
            },
            {
                "id":"181064951",
                "labels":[
                    "Company"
                ],
                "properties":{
                    "name":"安徽辉隆农资集团股份有限公司",
                    "gid":"181064951"
                }
            },
            {
                "id":"499395113",
                "labels":[
                    "Company"
                ],
                "properties":{
                    "name":"合肥德善小额贷款股份有限公司",
                    "gid":"499395113"
                }
            },
            {
                "id":"518729470",
                "labels":[
                    "Company"
                ],
                "properties":{
                    "name":"肥东县供销社泰昌资产管理有限公司",
                    "gid":"518729470"
                }
            },
            {
                "id":"4118865664",
                "labels":[
                    "Company"
                ],
                "properties":{
                    "name":"安徽润博仓储有限公司",
                    "gid":"4118865664"
                }
            },
            {
                "id":"1826156840&4118865664",
                "labels":[
                    "Human"
                ],
                "properties":{
                    "name":"卢向阳",
                    "gid":"1826156840"
                }
            },
            {
                "id":"3228082921",
                "labels":[
                    "Company"
                ],
                "properties":{
                    "name":"安徽大沙贸易有限公司",
                    "gid":"3228082921"
                }
            }
        ],
        "relationships":[
            {
                "type":"INVEST_C",
                "startNode":"3128510407",
                "endNode":"12321232",
                "properties":{
                    "labels":[
                        "参股"
                    ]
                }
            },
            {
                "type":"INVEST_C",
                "startNode":"3484794127",
                "endNode":"12321232",
                "properties":{
                    "labels":[
                        "参股"
                    ]
                }
            },
            {
                "type":"INVEST_C",
                "startNode":"3484794127",
                "endNode":"16845043",
                "properties":{
                    "labels":[
                        "参股"
                    ]
                }
            },
            {
                "type":"INVEST_C",
                "startNode":"16845043",
                "endNode":"181064951",
                "properties":{
                    "labels":[
                        "参股"
                    ]
                }
            },
            {
                "type":"INVEST_C",
                "startNode":"181064951",
                "endNode":"499395113",
                "properties":{
                    "labels":[
                        "参股"
                    ]
                }
            },
            {
                "type":"INVEST_C",
                "startNode":"518729470",
                "endNode":"499395113",
                "properties":{
                    "labels":[
                        "参股"
                    ]
                }
            },
            {
                "type":"INVEST_C",
                "startNode":"518729470",
                "endNode":"4118865664",
                "properties":{
                    "labels":[
                        "参股"
                    ]
                }
            },
            {
                "type":"INVEST_H",
                "startNode":"1826156840&4118865664",
                "endNode":"4118865664",
                "properties":{
                    "labels":[
                        "参股"
                    ]
                }
            },
            {
                "type":"INVEST_H",
                "startNode":"1826156840&4118865664",
                "endNode":"3228082921",
                "properties":{
                    "labels":[
                        "参股"
                    ]
                }
            },
            {
                "type":"SERVE",
                "startNode":"1826156840&4118865664",
                "endNode":"4118865664",
                "properties":{
                    "labels":[
                        "执行董事兼总经理"
                    ]
                }
            },
            {
                "type":"OWN",
                "startNode":"1826156840&4118865664",
                "endNode":"4118865664",
                "properties":{
                    "labels":[
                        "法人"
                    ]
                }
            }
        ]
    },
    "p_4":{
        "nodes":[
            {
                "id":"3128510407",
                "labels":[
                    "Company"
                ],
                "properties":{
                    "name":"中国建筑集团有限公司",
                    "gid":"3128510407"
                }
            },
            {
                "id":"1883105271&717278775",
                "labels":[
                    "Human"
                ],
                "properties":{
                    "name":"孙震",
                    "gid":"1883105271"
                }
            },
            {
                "id":"717278775",
                "labels":[
                    "Company"
                ],
                "properties":{
                    "name":"中建资本控股有限公司",
                    "gid":"717278775"
                }
            },
            {
                "id":"141005975",
                "labels":[
                    "Company"
                ],
                "properties":{
                    "name":"安徽国元信托有限责任公司",
                    "gid":"141005975"
                }
            },
            {
                "id":"2349394141",
                "labels":[
                    "Company"
                ],
                "properties":{
                    "name":"安徽新力金融股份有限公司",
                    "gid":"2349394141"
                }
            },
            {
                "id":"499395113",
                "labels":[
                    "Company"
                ],
                "properties":{
                    "name":"合肥德善小额贷款股份有限公司",
                    "gid":"499395113"
                }
            },
            {
                "id":"518729470",
                "labels":[
                    "Company"
                ],
                "properties":{
                    "name":"肥东县供销社泰昌资产管理有限公司",
                    "gid":"518729470"
                }
            },
            {
                "id":"4118865664",
                "labels":[
                    "Company"
                ],
                "properties":{
                    "name":"安徽润博仓储有限公司",
                    "gid":"4118865664"
                }
            },
            {
                "id":"1826156840&4118865664",
                "labels":[
                    "Human"
                ],
                "properties":{
                    "name":"卢向阳",
                    "gid":"1826156840"
                }
            },
            {
                "id":"3228082921",
                "labels":[
                    "Company"
                ],
                "properties":{
                    "name":"安徽大沙贸易有限公司",
                    "gid":"3228082921"
                }
            }
        ],
        "relationships":[
            {
                "type":"SERVE",
                "startNode":"1883105271&717278775",
                "endNode":"3128510407",
                "properties":{
                    "labels":[
                        "监事"
                    ]
                }
            },
            {
                "type":"SERVE",
                "startNode":"1883105271&717278775",
                "endNode":"717278775",
                "properties":{
                    "labels":[
                        "执行董事,总经理"
                    ]
                }
            },
            {
                "type":"INVEST_C",
                "startNode":"717278775",
                "endNode":"141005975",
                "properties":{
                    "labels":[
                        "参股"
                    ]
                }
            },
            {
                "type":"INVEST_C",
                "startNode":"2349394141",
                "endNode":"141005975",
                "properties":{
                    "labels":[
                        "参股"
                    ]
                }
            },
            {
                "type":"INVEST_C",
                "startNode":"2349394141",
                "endNode":"499395113",
                "properties":{
                    "labels":[
                        "参股"
                    ]
                }
            },
            {
                "type":"INVEST_C",
                "startNode":"518729470",
                "endNode":"499395113",
                "properties":{
                    "labels":[
                        "参股"
                    ]
                }
            },
            {
                "type":"INVEST_C",
                "startNode":"518729470",
                "endNode":"4118865664",
                "properties":{
                    "labels":[
                        "参股"
                    ]
                }
            },
            {
                "type":"INVEST_H",
                "startNode":"1826156840&4118865664",
                "endNode":"4118865664",
                "properties":{
                    "labels":[
                        "参股"
                    ]
                }
            },
            {
                "type":"INVEST_H",
                "startNode":"1826156840&4118865664",
                "endNode":"3228082921",
                "properties":{
                    "labels":[
                        "参股"
                    ]
                }
            },
            {
                "type":"SERVE",
                "startNode":"1826156840&4118865664",
                "endNode":"4118865664",
                "properties":{
                    "labels":[
                        "执行董事兼总经理"
                    ]
                }
            },
            {
                "type":"OWN",
                "startNode":"1826156840&4118865664",
                "endNode":"4118865664",
                "properties":{
                    "labels":[
                        "法人"
                    ]
                }
            },
            {
                "type":"OWN",
                "startNode":"1883105271&717278775",
                "endNode":"717278775",
                "properties":{
                    "labels":[
                        "法人"
                    ]
                }
            }
        ]
    },
    "p_5":{
        "nodes":[
            {
                "id":"3128510407",
                "labels":[
                    "Company"
                ],
                "properties":{
                    "name":"中国建筑集团有限公司",
                    "gid":"3128510407"
                }
            },
            {
                "id":"12321232",
                "labels":[
                    "Company"
                ],
                "properties":{
                    "name":"中国建筑股份有限公司",
                    "gid":"12321232"
                }
            },
            {
                "id":"717278775",
                "labels":[
                    "Company"
                ],
                "properties":{
                    "name":"中建资本控股有限公司",
                    "gid":"717278775"
                }
            },
            {
                "id":"141005975",
                "labels":[
                    "Company"
                ],
                "properties":{
                    "name":"安徽国元信托有限责任公司",
                    "gid":"141005975"
                }
            },
            {
                "id":"2349394141",
                "labels":[
                    "Company"
                ],
                "properties":{
                    "name":"安徽新力金融股份有限公司",
                    "gid":"2349394141"
                }
            },
            {
                "id":"499395113",
                "labels":[
                    "Company"
                ],
                "properties":{
                    "name":"合肥德善小额贷款股份有限公司",
                    "gid":"499395113"
                }
            },
            {
                "id":"518729470",
                "labels":[
                    "Company"
                ],
                "properties":{
                    "name":"肥东县供销社泰昌资产管理有限公司",
                    "gid":"518729470"
                }
            },
            {
                "id":"4118865664",
                "labels":[
                    "Company"
                ],
                "properties":{
                    "name":"安徽润博仓储有限公司",
                    "gid":"4118865664"
                }
            },
            {
                "id":"1826156840&4118865664",
                "labels":[
                    "Human"
                ],
                "properties":{
                    "name":"卢向阳",
                    "gid":"1826156840"
                }
            },
            {
                "id":"3228082921",
                "labels":[
                    "Company"
                ],
                "properties":{
                    "name":"安徽大沙贸易有限公司",
                    "gid":"3228082921"
                }
            }
        ],
        "relationships":[
            {
                "type":"INVEST_C",
                "startNode":"3128510407",
                "endNode":"12321232",
                "properties":{
                    "labels":[
                        "参股"
                    ]
                }
            },
            {
                "type":"INVEST_C",
                "startNode":"12321232",
                "endNode":"717278775",
                "properties":{
                    "labels":[
                        "参股"
                    ]
                }
            },
            {
                "type":"INVEST_C",
                "startNode":"717278775",
                "endNode":"141005975",
                "properties":{
                    "labels":[
                        "参股"
                    ]
                }
            },
            {
                "type":"INVEST_C",
                "startNode":"2349394141",
                "endNode":"141005975",
                "properties":{
                    "labels":[
                        "参股"
                    ]
                }
            },
            {
                "type":"INVEST_C",
                "startNode":"2349394141",
                "endNode":"499395113",
                "properties":{
                    "labels":[
                        "参股"
                    ]
                }
            },
            {
                "type":"INVEST_C",
                "startNode":"518729470",
                "endNode":"499395113",
                "properties":{
                    "labels":[
                        "参股"
                    ]
                }
            },
            {
                "type":"INVEST_C",
                "startNode":"518729470",
                "endNode":"4118865664",
                "properties":{
                    "labels":[
                        "参股"
                    ]
                }
            },
            {
                "type":"INVEST_H",
                "startNode":"1826156840&4118865664",
                "endNode":"4118865664",
                "properties":{
                    "labels":[
                        "参股"
                    ]
                }
            },
            {
                "type":"INVEST_H",
                "startNode":"1826156840&4118865664",
                "endNode":"3228082921",
                "properties":{
                    "labels":[
                        "参股"
                    ]
                }
            },
            {
                "type":"SERVE",
                "startNode":"1826156840&4118865664",
                "endNode":"4118865664",
                "properties":{
                    "labels":[
                        "执行董事兼总经理"
                    ]
                }
            },
            {
                "type":"OWN",
                "startNode":"1826156840&4118865664",
                "endNode":"4118865664",
                "properties":{
                    "labels":[
                        "法人"
                    ]
                }
            }
        ]
    },
    "p_0":{
        "nodes":[
            {
                "id":"1883105271&717278775",
                "labels":[
                    "Human"
                ],
                "properties":{
                    "name":"孙震",
                    "gid":"1883105271"
                }
            },
            {
                "id":"373897708",
                "labels":[
                    "Company"
                ],
                "properties":{
                    "name":"安徽国元投资有限责任公司",
                    "gid":"373897708"
                }
            },
            {
                "id":"16845043",
                "labels":[
                    "Company"
                ],
                "properties":{
                    "name":"中信建投证券股份有限公司",
                    "gid":"16845043"
                }
            },
            {
                "id":"518729470",
                "labels":[
                    "Company"
                ],
                "properties":{
                    "name":"肥东县供销社泰昌资产管理有限公司",
                    "gid":"518729470"
                }
            },
            {
                "id":"12321232",
                "labels":[
                    "Company"
                ],
                "properties":{
                    "name":"中国建筑股份有限公司",
                    "gid":"12321232"
                }
            },
            {
                "id":"141005975",
                "labels":[
                    "Company"
                ],
                "properties":{
                    "name":"安徽国元信托有限责任公司",
                    "gid":"141005975"
                }
            },
            {
                "id":"3228082921",
                "labels":[
                    "Company"
                ],
                "properties":{
                    "name":"安徽大沙贸易有限公司",
                    "gid":"3228082921"
                }
            },
            {
                "id":"717278775",
                "labels":[
                    "Company"
                ],
                "properties":{
                    "name":"中建资本控股有限公司",
                    "gid":"717278775"
                }
            },
            {
                "id":"181064951",
                "labels":[
                    "Company"
                ],
                "properties":{
                    "name":"安徽辉隆农资集团股份有限公司",
                    "gid":"181064951"
                }
            },
            {
                "id":"2349394141",
                "labels":[
                    "Company"
                ],
                "properties":{
                    "name":"安徽新力金融股份有限公司",
                    "gid":"2349394141"
                }
            },
            {
                "id":"3128510407",
                "labels":[
                    "Company"
                ],
                "properties":{
                    "name":"中国建筑集团有限公司",
                    "gid":"3128510407"
                }
            },
            {
                "id":"499395113",
                "labels":[
                    "Company"
                ],
                "properties":{
                    "name":"合肥德善小额贷款股份有限公司",
                    "gid":"499395113"
                }
            },
            {
                "id":"4118865664",
                "labels":[
                    "Company"
                ],
                "properties":{
                    "name":"安徽润博仓储有限公司",
                    "gid":"4118865664"
                }
            },
            {
                "id":"3484794127",
                "labels":[
                    "Company"
                ],
                "properties":{
                    "name":"香港中央结算有限公司",
                    "gid":"3484794127"
                }
            },
            {
                "id":"1826156840&4118865664",
                "labels":[
                    "Human"
                ],
                "properties":{
                    "name":"卢向阳",
                    "gid":"1826156840"
                }
            }
        ],
        "relationships":[
            {
                "type":"INVEST_C",
                "startNode":"518729470",
                "endNode":"4118865664",
                "properties":{
                    "labels":[
                        "参股"
                    ]
                }
            },
            {
                "type":"SERVE",
                "startNode":"1883105271&717278775",
                "endNode":"717278775",
                "properties":{
                    "labels":[
                        "执行董事,总经理"
                    ]
                }
            },
            {
                "type":"INVEST_C",
                "startNode":"717278775",
                "endNode":"373897708",
                "properties":{
                    "labels":[
                        "参股"
                    ]
                }
            },
            {
                "type":"INVEST_C",
                "startNode":"518729470",
                "endNode":"499395113",
                "properties":{
                    "labels":[
                        "参股"
                    ]
                }
            },
            {
                "type":"INVEST_C",
                "startNode":"3484794127",
                "endNode":"12321232",
                "properties":{
                    "labels":[
                        "参股"
                    ]
                }
            },
            {
                "type":"INVEST_C",
                "startNode":"3484794127",
                "endNode":"16845043",
                "properties":{
                    "labels":[
                        "参股"
                    ]
                }
            },
            {
                "type":"SERVE",
                "startNode":"1883105271&717278775",
                "endNode":"3128510407",
                "properties":{
                    "labels":[
                        "监事"
                    ]
                }
            },
            {
                "type":"INVEST_C",
                "startNode":"2349394141",
                "endNode":"373897708",
                "properties":{
                    "labels":[
                        "参股"
                    ]
                }
            },
            {
                "type":"INVEST_C",
                "startNode":"12321232",
                "endNode":"717278775",
                "properties":{
                    "labels":[
                        "参股"
                    ]
                }
            },
            {
                "type":"INVEST_H",
                "startNode":"1826156840&4118865664",
                "endNode":"3228082921",
                "properties":{
                    "labels":[
                        "参股"
                    ]
                }
            },
            {
                "type":"SERVE",
                "startNode":"1826156840&4118865664",
                "endNode":"4118865664",
                "properties":{
                    "labels":[
                        "执行董事兼总经理"
                    ]
                }
            },
            {
                "type":"INVEST_C",
                "startNode":"16845043",
                "endNode":"181064951",
                "properties":{
                    "labels":[
                        "参股"
                    ]
                }
            },
            {
                "type":"INVEST_C",
                "startNode":"717278775",
                "endNode":"141005975",
                "properties":{
                    "labels":[
                        "参股"
                    ]
                }
            },
            {
                "type":"INVEST_C",
                "startNode":"181064951",
                "endNode":"499395113",
                "properties":{
                    "labels":[
                        "参股"
                    ]
                }
            },
            {
                "type":"INVEST_C",
                "startNode":"2349394141",
                "endNode":"141005975",
                "properties":{
                    "labels":[
                        "参股"
                    ]
                }
            },
            {
                "type":"INVEST_C",
                "startNode":"3128510407",
                "endNode":"12321232",
                "properties":{
                    "labels":[
                        "参股"
                    ]
                }
            },
            {
                "type":"OWN",
                "startNode":"1883105271&717278775",
                "endNode":"717278775",
                "properties":{
                    "labels":[
                        "法人"
                    ]
                }
            },
            {
                "type":"INVEST_C",
                "startNode":"2349394141",
                "endNode":"499395113",
                "properties":{
                    "labels":[
                        "参股"
                    ]
                }
            },
            {
                "type":"OWN",
                "startNode":"1826156840&4118865664",
                "endNode":"4118865664",
                "properties":{
                    "labels":[
                        "法人"
                    ]
                }
            },
            {
                "type":"INVEST_H",
                "startNode":"1826156840&4118865664",
                "endNode":"4118865664",
                "properties":{
                    "labels":[
                        "参股"
                    ]
                }
            }
        ]
    }
}