{"p_0": {"nodes": [{"id": "2349961999", "labels": ["Company"], "properties": {"name": "\u6c5f\u9634\u5e02\u9a7b\u65e0\u9521\u7269\u8d44\u4e2d\u8f6c\u50a8\u8fd0\u516c\u53f8", "gid": "2349961999"}}, {"id": "3429797724", "labels": ["Company"], "properties": {"name": "\u6d59\u5546\u4e2d\u62d3\u96c6\u56e2\uff08\u8d35\u5dde\uff09\u6709\u9650\u516c\u53f8", "gid": "3429797724"}}], "relationships": []}, "p_1": {"nodes": [{"id": "2349961999", "labels": ["Company"], "properties": {"name": "\u6c5f\u9634\u5e02\u9a7b\u65e0\u9521\u7269\u8d44\u4e2d\u8f6c\u50a8\u8fd0\u516c\u53f8", "gid": "2349961999"}}, {"id": "3429797724", "labels": ["Company"], "properties": {"name": "\u6d59\u5546\u4e2d\u62d3\u96c6\u56e2\uff08\u8d35\u5dde\uff09\u6709\u9650\u516c\u53f8", "gid": "3429797724"}}], "relationships": []}}